core/__init__.py
core/google_auth/__init__.py
core/google_auth/google.py
core/oauth/__init__.py
core/oauth/apple.py
core/oauth/google.py
core/oauth/secrets.py
oauth_core_lib-1.0.0.dist-info/LICENSE
oauth_core_lib-1.0.0.dist-info/METADATA
oauth_core_lib-1.0.0.dist-info/WHEEL
oauth_core_lib-1.0.0.dist-info/top_level.txt
oauth_core_lib-1.0.0.dist-info/RECORD
