Metadata-Version: 2.1
Name: oauth-core-lib
Version: 1.0.0
Summary: A Python library for handling OAuth authentication, designed for use in third-party applications. 
Home-page: https://github.com/limFakson/Python_OAuth_Core
Author: limFakson
Author-email: fakeyejoshua2005@gmail.com
License: MIT
Classifier: Programming Language :: Python :: 3
Classifier: License :: OSI Approved :: MIT License
Classifier: Operating System :: OS Independent
Requires-Python: >=3.6
License-File: LICENSE
Requires-Dist: python-dotenv>=1.0.1
Requires-Dist: requests>=2.25.1
